MANIFEST.in
README.md
notmyip.py
requirements.txt
setup.py
not_my_ip.egg-info/PKG-INFO
not_my_ip.egg-info/SOURCES.txt
not_my_ip.egg-info/dependency_links.txt
not_my_ip.egg-info/entry_points.txt
not_my_ip.egg-info/requires.txt
not_my_ip.egg-info/top_level.txt