Metadata-Version: 2.1
Name: not-my-ip
Version: 0.0.4
Summary: A CLI tool to generate a random IP address that is not your own
Author: Samuel Gunter
Author-email: sgunter@utexas.edu
